[
  {
    "_id": "1",
    "image": "/img/services-dummy/pulau-komodo.jpg",
    "title": "Cuci sepatu high dark clean",
    "price": "350000",
    "qty": 0
  },
  {
    "_id": "2",
    "image": "/img/services-dummy/pulau-komodo.jpg",
    "title": "Cuci tas ukuran besar",
    "price": "400000",
    "qty": 0
  },
  {
    "_id": "3",
    "image": "/img/services-dummy/pulau-komodo.jpg",
    "title": "Cuci sneaklin order shop",
    "price": "210000",
    "qty": 0
  },
  {
    "_id": "4",
    "image": "/img/services-dummy/pulau-komodo.jpg",
    "title": "Cuci sepatu medium show",
    "price": "120000",
    "qty": 0
  },
  {
    "_id": "5",
    "image": "/img/services-dummy/pulau-komodo.jpg",
    "title": "Cuci topi 50pcs",
    "price": "300000",
    "qty": 0
  }
]
